ontology_project/Ec3EpdCsv_to_Ec3Epd_onto1.py
ontology_project/McpCsv_to_Mcp_onto3.py
ontology_project/TruCsv_to_Tru_onto2.py
ontology_project/__init__.py
ontology_project/merge_ontology.py
ontology_project/runner.py
ontology_project-0.1.2.dist-info/LICENSE
ontology_project-0.1.2.dist-info/METADATA
ontology_project-0.1.2.dist-info/WHEEL
ontology_project-0.1.2.dist-info/entry_points.txt
ontology_project-0.1.2.dist-info/top_level.txt
ontology_project-0.1.2.dist-info/RECORD
